bosa_server_plugins.cpython-312-x86_64-linux-gnu.so
bosa_server_plugins.pyi
bosa_server_plugins/__init__.pyi
bosa_server_plugins/auth/__init__.pyi
bosa_server_plugins/auth/bearer.pyi
bosa_server_plugins/auth/scheme.pyi
bosa_server_plugins/background_task/__init__.pyi
bosa_server_plugins/background_task/constant.pyi
bosa_server_plugins/background_task/utils.pyi
bosa_server_plugins/catapa/__init__.pyi
bosa_server_plugins/catapa/plugin.pyi
bosa_server_plugins/catapa/router.pyi
bosa_server_plugins/catapa/auth/__init__.pyi
bosa_server_plugins/catapa/auth/auth.pyi
bosa_server_plugins/catapa/response/__init__.pyi
bosa_server_plugins/catapa/response/user.pyi
bosa_server_plugins/catapa/routes/__init__.pyi
bosa_server_plugins/catapa/routes/user.pyi
bosa_server_plugins/catapa/services/__init__.pyi
bosa_server_plugins/catapa/services/base.pyi
bosa_server_plugins/catapa/services/user.pyi
bosa_server_plugins/code_interpreter/__init__.pyi
bosa_server_plugins/code_interpreter/constant.pyi
bosa_server_plugins/code_interpreter/plugin.pyi
bosa_server_plugins/code_interpreter/router.pyi
bosa_server_plugins/code_interpreter/helper/__init__.pyi
bosa_server_plugins/code_interpreter/helper/execute_code.pyi
bosa_server_plugins/code_interpreter/helper/file_watcher.pyi
bosa_server_plugins/code_interpreter/requests/__init__.pyi
bosa_server_plugins/code_interpreter/requests/execute_code.pyi
bosa_server_plugins/code_interpreter/routes/__init__.pyi
bosa_server_plugins/code_interpreter/routes/execute_code.pyi
bosa_server_plugins/code_interpreter/service/__init__.pyi
bosa_server_plugins/code_interpreter/service/sandbox_creator.pyi
bosa_server_plugins/common/__init__.pyi
bosa_server_plugins/common/cache.pyi
bosa_server_plugins/common/callback.pyi
bosa_server_plugins/common/dict.pyi
bosa_server_plugins/common/email.pyi
bosa_server_plugins/common/exception.pyi
bosa_server_plugins/common/filter.pyi
bosa_server_plugins/common/mimetypes.pyi
bosa_server_plugins_binary-0.14.9.dist-info/METADATA
bosa_server_plugins_binary-0.14.9.dist-info/WHEEL
bosa_server_plugins_binary-0.14.9.dist-info/top_level.txt
bosa_server_plugins_binary-0.14.9.dist-info/RECORD
