Metadata-Version: 2.2
Name: bosa-server-plugins-binary
Version: 0.14.9
Summary: BOSA Server Plugins
Author-email: Bosa Engineers <bosa-eng@gdplabs.id>
Requires-Python: <3.14,>=3.11
Requires-Dist: requests>=2.32.4
Requires-Dist: gql[all]>=3.5.0
Requires-Dist: pygithub>=2.6.1
Requires-Dist: google-api-python-client>=2.163.0
Requires-Dist: google-auth-httplib2>=0.2.0
Requires-Dist: google-auth-oauthlib>=1.2.1
Requires-Dist: celery>=5.5.2
Requires-Dist: python-magic<0.5.0,>=0.4.27; sys_platform != "win32"
Requires-Dist: python-magic-bin<0.5.0,>=0.4.14; sys_platform == "win32"
Requires-Dist: python-docx>=1.1.2
Requires-Dist: mistune>=3.1.3
Requires-Dist: pypandoc-binary>=1.15
Requires-Dist: bosa-core-binary[all]==0.9.6
Requires-Dist: tweepy[async]>=4.16.0
Requires-Dist: urllib3<3.0.0,>=2.5.0
Requires-Dist: redis<6.0.0,>=5.2.1
Requires-Dist: aci-sdk>=1.0.0b2
Requires-Dist: pandas<3.0.0,>=2.3.3
Requires-Dist: markitdown[docx,pdf,pptx]<0.2.0,>=0.1.3
Requires-Dist: gllm-tools-binary>=0.1.4
Requires-Dist: fastmcp<3.0.0.0,>=2.13.0.1
Requires-Dist: auditwheel>=6.5.0
Requires-Dist: patchelf>=0.17.2.4
Provides-Extra: dev
Requires-Dist: pre-commit<4.0.0,>=3.6.2; extra == "dev"
Requires-Dist: pytest<9.0.0,>=8.3.4; extra == "dev"
Requires-Dist: pytest-mock<4.0.0,>=3.14.0; extra == "dev"
Requires-Dist: pytest-asyncio<1.0.0,>=0.25.3; extra == "dev"
Requires-Dist: coverage<8.0.0,>=7.6.10; extra == "dev"
Requires-Dist: mypy<2.0.0,>=1.11.2; extra == "dev"
Requires-Dist: ruff<1.0.0,>=0.9.9; extra == "dev"
Requires-Dist: pytest-cov<6.0.0,>=5.0.0; extra == "dev"
Requires-Dist: black>=24.3.0; extra == "dev"
